Metadata-Version: 2.4
Name: apolo-sdk
Version: 26.1.0
Summary: Apolo SDK
Home-page: https://github.com/neuro-inc/platform-client-python
Author: Apolo Team
Author-email: dev@apolo.us
License: Apache 2
Classifier: Programming Language :: Python :: 3
Classifier: Programming Language :: Python :: 3.10
Classifier: Programming Language :: Python :: 3.11
Classifier: Programming Language :: Python :: 3.12
Classifier: Programming Language :: Python :: 3.13
Classifier: Operating System :: OS Independent
Classifier: Development Status :: 4 - Beta
Classifier: Environment :: Console
Classifier: Intended Audience :: Developers
Classifier: Intended Audience :: Science/Research
Classifier: Intended Audience :: Information Technology
Classifier: Topic :: Scientific/Engineering :: Artificial Intelligence
Classifier: Topic :: Software Development
Classifier: Topic :: Utilities
Classifier: License :: OSI Approved :: Apache Software License
Requires-Python: >=3.10.0
License-File: LICENSE
Requires-Dist: aiohttp>=3.11.3
Requires-Dist: pyyaml>=5.0
Requires-Dist: python-jose>=3.3.0
Requires-Dist: python-dateutil>=2.7.0
Requires-Dist: aiobotocore<4.0,>=2.3.0
Requires-Dist: aiodocker>=0.24.0
Requires-Dist: certifi
Requires-Dist: toml>=0.10.0
Requires-Dist: azure-storage-blob!=12.9.0,>=12.8.1
Requires-Dist: google-auth>=2.0.2
Requires-Dist: importlib_metadata>=4.11.4; python_version < "3.11"
Requires-Dist: packaging>=20.4
Requires-Dist: neuro-admin-client==25.12.0
Requires-Dist: neuro-config-client==25.12.0
Dynamic: license-file
